pynwsradar/__init__.py
pynwsradar/console_script.py
pynwsradar/const.py
pynwsradar/nexrad.py
pynwsradar/version.py
pynwsradar-0.0.1.dist-info/LICENSE.rst
pynwsradar-0.0.1.dist-info/METADATA
pynwsradar-0.0.1.dist-info/WHEEL
pynwsradar-0.0.1.dist-info/entry_points.txt
pynwsradar-0.0.1.dist-info/top_level.txt
pynwsradar-0.0.1.dist-info/RECORD
